{"assets/1.json":["assets/1.json"],"assets/1st.png":["assets/1st.png"],"assets/2.json":["assets/2.json"],"assets/2nd.png":["assets/2nd.png"],"assets/3.json":["assets/3.json"],"assets/3rd.png":["assets/3rd.png"],"assets/4.json":["assets/4.json"],"assets/4th.png":["assets/4th.png"],"assets/5th.json":["assets/5th.json"],"assets/5th.png":["assets/5th.png"],"assets/6th.png":["assets/6th.png"],"assets/7th.png":["assets/7th.png"],"assets/bhaiya.jpg":["assets/bhaiya.jpg"],"assets/fonts/Roman_Bold.ttf":["assets/fonts/Roman_Bold.ttf"],"assets/location.png":["assets/location.png"],"assets/mama.jpg":["assets/mama.jpg"],"packages/cupertino_icons/assets/CupertinoIcons.ttf":["packages/cupertino_icons/assets/CupertinoIcons.ttf"]}